<?xml version="1.0" encoding="utf-8" standalone="yes"?>
<SexyContent FileVersion="07.00.00" MinimumRequiredVersion="07.04.02" ModuleVersion="14.07.03" ExportDate="2023-04-27T01:48:10.2789298-03:00">
  <Header>
    <App Guid="81b3e8a5-9819-472a-a300-f0eb8e3d2d06" />
    <Language Default="pt-br" />
    <Dimensions>
      <Dimension DimensionID="3" Name="Portuguese (Brazil)" SystemKey="" ExternalKey="pt-BR" Active="true" />
    </Dimensions>
  </Header>
  <AttributeSets>
    <AttributeSet StaticName="App-Resources" Name="App-Resources" Description="Stores resources like translations for an app" Scope="System.App" AlwaysShareConfiguration="false">
      <Attributes />
    </AttributeSet>
    <AttributeSet StaticName="App-Settings" Name="App-Settings" Description="Stores settings for an app" Scope="System.App" AlwaysShareConfiguration="false">
      <Attributes />
    </AttributeSet>
    <AttributeSet StaticName="3168c0b7-c5b9-4aa8-9ada-773890339e58" Name="Location" Description="Location / Address" Scope="Default" AlwaysShareConfiguration="false">
      <Attributes>
        <Attribute StaticName="Title" Type="String" IsTitle="true">
          <Entity TargetType="2" AssignmentObjectType="EAV Field Properties" AttributeSetStaticName="@All" AttributeSetName="@All" EntityGUID="4e1dc733-fcd8-4c5b-b16a-a0f207437a24" Json="True" KeyNumber="1608">
            <Value Key="CustomJavaScript" Value="" Type="String" />
            <Value Key="DefaultValue" Value="" Type="String" />
            <Value Key="Disabled" Value="False" Type="Boolean" />
            <Value Key="DisableTranslation" Value="False" Type="Boolean" />
            <Value Key="InputType" Value="string-default" Type="String" />
            <Value Key="Name" Value="Título / empresa" Type="String" />
            <Value Key="Notes" Value="&lt;p&gt;Habitualmente o nome da empresa, mas tamb&amp;eacute;m pode ser um t&amp;iacute;tulo como &lt;em&gt;Local de constru&amp;ccedil;&amp;atilde;o&lt;/em&gt;&lt;/p&gt;" Type="String" />
            <Value Key="Placeholder" Value="" Type="String" />
            <Value Key="Required" Value="True" Type="Boolean" />
            <Value Key="ValidationRegExJavaScript" Value="" Type="String" />
            <Value Key="VisibleInEditUI" Value="True" Type="Boolean" />
          </Entity>
          <Entity TargetType="2" AssignmentObjectType="EAV Field Properties" AttributeSetStaticName="@String" AttributeSetName="@String" EntityGUID="721b09a6-7814-49a4-b85f-2cea2ad11791" Json="True" KeyNumber="1608">
            <Value Key="DropdownValues" Value="" Type="String" />
            <Value Key="InputType" Value="" Type="String" />
          </Entity>
          <Entity TargetType="2" AssignmentObjectType="EAV Field Properties" AttributeSetStaticName="@string-default" AttributeSetName="@string-default" EntityGUID="fbcccbe9-7af1-48b8-81ff-b8415c5e258c" Json="True" KeyNumber="1608">
            <Value Key="InputFontFamily" Value="" Type="String" />
          </Entity>
        </Attribute>
        <Attribute StaticName="Description" Type="String" IsTitle="false">
          <Entity TargetType="2" AssignmentObjectType="EAV Field Properties" AttributeSetStaticName="@All" AttributeSetName="@All" EntityGUID="0046030d-25d7-4584-aa43-bb08f0df7a84" Json="True" KeyNumber="1609">
            <Value Key="CustomJavaScript" Value="" Type="String" />
            <Value Key="DefaultValue" Value="" Type="String" />
            <Value Key="Disabled" Value="False" Type="Boolean" />
            <Value Key="DisableTranslation" Value="False" Type="Boolean" />
            <Value Key="InputType" Value="string-wysiwyg" Type="String" />
            <Value Key="Name" Value="Descrição curta" Type="String" />
            <Value Key="Notes" Value="&lt;p&gt;Descri&amp;ccedil;&amp;atilde;o do endere&amp;ccedil;o - ser&amp;aacute; mostrado em alguns templates.&lt;/p&gt;" Type="String" />
            <Value Key="Placeholder" Value="" Type="String" />
            <Value Key="Required" Value="False" Type="Boolean" />
            <Value Key="ValidationRegExJavaScript" Value="" Type="String" />
            <Value Key="VisibleInEditUI" Value="True" Type="Boolean" />
          </Entity>
          <Entity TargetType="2" AssignmentObjectType="EAV Field Properties" AttributeSetStaticName="@String" AttributeSetName="@String" EntityGUID="78d64ac4-6050-41ec-b98c-8a8f8249983d" Json="True" KeyNumber="1609">
            <Value Key="DropdownValues" Value="" Type="String" />
            <Value Key="InputType" Value="wysiwyg" Type="String" />
            <Value Key="RowCount" Value="1" Type="Number" />
          </Entity>
          <Entity TargetType="2" AssignmentObjectType="EAV Field Properties" AttributeSetStaticName="@string-wysiwyg" AttributeSetName="@string-wysiwyg" EntityGUID="6e8f971d-486f-4897-8354-20d8118c3411" Json="True" KeyNumber="1609">
            <Value Key="ButtonAdvanced" Value="" Type="String" />
            <Value Key="ButtonSource" Value="" Type="String" />
            <Value Key="ContentCss" Value="" Type="Hyperlink" />
            <Value Key="Dialog" Value="" Type="String" />
            <Value Key="InlineInitialHeight" Value="" Type="String" />
          </Entity>
        </Attribute>
        <Attribute StaticName="Icon" Type="Hyperlink" IsTitle="false">
          <Entity TargetType="2" AssignmentObjectType="EAV Field Properties" AttributeSetStaticName="@All" AttributeSetName="@All" EntityGUID="6bb0cc1d-19f0-4287-80c2-73edc1d8a259" Json="True" KeyNumber="1641">
            <Value Key="CustomJavaScript" Value="" Type="String">
              <Dimension DimensionID="3" ReadOnly="false" />
            </Value>
            <Value Key="DefaultValue" Value="https://icon-library.com/images/google-maps-bus-icon/google-maps-bus-icon-3.jpg" Type="String">
              <Dimension DimensionID="3" ReadOnly="false" />
            </Value>
            <Value Key="Disabled" Value="False" Type="Boolean">
              <Dimension DimensionID="3" ReadOnly="false" />
            </Value>
            <Value Key="DisableTranslation" Value="False" Type="Boolean">
              <Dimension DimensionID="3" ReadOnly="false" />
            </Value>
            <Value Key="InputType" Value="hyperlink-default" Type="String">
              <Dimension DimensionID="3" ReadOnly="false" />
            </Value>
            <Value Key="Name" Value="Icon" Type="String">
              <Dimension DimensionID="3" ReadOnly="false" />
            </Value>
            <Value Key="Notes" Value="" Type="String">
              <Dimension DimensionID="3" ReadOnly="false" />
            </Value>
            <Value Key="Placeholder" Value="" Type="String">
              <Dimension DimensionID="3" ReadOnly="false" />
            </Value>
            <Value Key="Required" Value="False" Type="Boolean">
              <Dimension DimensionID="3" ReadOnly="false" />
            </Value>
            <Value Key="ValidationRegExJavaScript" Value="" Type="String">
              <Dimension DimensionID="3" ReadOnly="false" />
            </Value>
            <Value Key="VisibleInEditUI" Value="True" Type="Boolean">
              <Dimension DimensionID="3" ReadOnly="false" />
            </Value>
          </Entity>
          <Entity TargetType="2" AssignmentObjectType="EAV Field Properties" AttributeSetStaticName="@Hyperlink" AttributeSetName="@Hyperlink" EntityGUID="a2940a3b-f604-4cf9-a7e7-53ede7d671d0" Json="True" KeyNumber="1641">
            <Value Key="Buttons" Value="adam,more" Type="String">
              <Dimension DimensionID="3" ReadOnly="false" />
            </Value>
            <Value Key="DefaultDialog" Value="" Type="String">
              <Dimension DimensionID="3" ReadOnly="false" />
            </Value>
            <Value Key="FileFilter" Value="" Type="String">
              <Dimension DimensionID="3" ReadOnly="false" />
            </Value>
            <Value Key="Paths" Value="" Type="String">
              <Dimension DimensionID="3" ReadOnly="false" />
            </Value>
            <Value Key="ServerResourceMapping" Value="" Type="String">
              <Dimension DimensionID="3" ReadOnly="false" />
            </Value>
            <Value Key="ShowAdam" Value="True" Type="Boolean">
              <Dimension DimensionID="3" ReadOnly="false" />
            </Value>
            <Value Key="ShowFileManager" Value="False" Type="Boolean">
              <Dimension DimensionID="3" ReadOnly="false" />
            </Value>
            <Value Key="ShowImageManager" Value="False" Type="Boolean">
              <Dimension DimensionID="3" ReadOnly="false" />
            </Value>
            <Value Key="ShowPagePicker" Value="False" Type="Boolean">
              <Dimension DimensionID="3" ReadOnly="false" />
            </Value>
          </Entity>
        </Attribute>
        <Attribute StaticName="AddressGroup" Type="Empty" IsTitle="false">
          <Entity TargetType="2" AssignmentObjectType="EAV Field Properties" AttributeSetStaticName="@All" AttributeSetName="@All" EntityGUID="c05004a7-7bc4-4724-a062-4da34d45a3de" Json="True" KeyNumber="1610">
            <Value Key="DefaultValue" Value="" Type="String" />
            <Value Key="Disabled" Value="False" Type="Boolean" />
            <Value Key="InputType" Value="empty-default" Type="String" />
            <Value Key="Name" Value="Endereço" Type="String" />
            <Value Key="Notes" Value="" Type="String" />
            <Value Key="Required" Value="False" Type="Boolean" />
            <Value Key="ValidationRegExJavaScript" Value="" Type="String" />
            <Value Key="VisibleInEditUI" Value="True" Type="Boolean" />
          </Entity>
          <Entity TargetType="2" AssignmentObjectType="EAV Field Properties" AttributeSetStaticName="@empty-default" AttributeSetName="@empty-default" EntityGUID="a969cfe0-08c1-43ae-a128-dc704a733429" Json="True" KeyNumber="1610">
            <Value Key="DefaultCollapsed" Value="False" Type="Boolean" />
          </Entity>
        </Attribute>
        <Attribute StaticName="Street" Type="String" IsTitle="false">
          <Entity TargetType="2" AssignmentObjectType="EAV Field Properties" AttributeSetStaticName="@All" AttributeSetName="@All" EntityGUID="4ff8c22b-2b90-4616-957a-aaae56eb5e7a" Json="True" KeyNumber="1611">
            <Value Key="DefaultValue" Value="" Type="String" />
            <Value Key="Disabled" Value="False" Type="Boolean" />
            <Value Key="InputType" Value="string-default" Type="String" />
            <Value Key="Name" Value="Rua" Type="String" />
            <Value Key="Notes" Value="" Type="String" />
            <Value Key="Required" Value="False" Type="Boolean" />
            <Value Key="ValidationRegExJavaScript" Value="" Type="String" />
            <Value Key="VisibleInEditUI" Value="True" Type="Boolean" />
          </Entity>
          <Entity TargetType="2" AssignmentObjectType="EAV Field Properties" AttributeSetStaticName="@String" AttributeSetName="@String" EntityGUID="9dd6de75-a572-43e9-bd19-beedc8cfa384" Json="True" KeyNumber="1611" />
          <Entity TargetType="2" AssignmentObjectType="EAV Field Properties" AttributeSetStaticName="@string-default" AttributeSetName="@string-default" EntityGUID="965d6148-8376-4fec-af51-c5c94beda097" Json="True" KeyNumber="1611">
            <Value Key="RowCount" Value="3" Type="Number" />
          </Entity>
        </Attribute>
        <Attribute StaticName="ZipCode" Type="String" IsTitle="false">
          <Entity TargetType="2" AssignmentObjectType="EAV Field Properties" AttributeSetStaticName="@All" AttributeSetName="@All" EntityGUID="4c5645ec-c1d7-4075-b47b-22288af85777" Json="True" KeyNumber="1612">
            <Value Key="DefaultValue" Value="" Type="String" />
            <Value Key="Disabled" Value="False" Type="Boolean" />
            <Value Key="InputType" Value="string-default" Type="String" />
            <Value Key="Name" Value="Código Postal" Type="String" />
            <Value Key="Notes" Value="" Type="String" />
            <Value Key="Required" Value="False" Type="Boolean" />
            <Value Key="ValidationRegExJavaScript" Value="" Type="String" />
            <Value Key="VisibleInEditUI" Value="True" Type="Boolean" />
          </Entity>
          <Entity TargetType="2" AssignmentObjectType="EAV Field Properties" AttributeSetStaticName="@String" AttributeSetName="@String" EntityGUID="654bcf6a-e2dc-42f4-b346-fca7705b7780" Json="True" KeyNumber="1612" />
          <Entity TargetType="2" AssignmentObjectType="EAV Field Properties" AttributeSetStaticName="@string-default" AttributeSetName="@string-default" EntityGUID="cb573b32-1fdd-49b5-914e-aa09532ef1f3" Json="True" KeyNumber="1612" />
        </Attribute>
        <Attribute StaticName="City" Type="String" IsTitle="false">
          <Entity TargetType="2" AssignmentObjectType="EAV Field Properties" AttributeSetStaticName="@All" AttributeSetName="@All" EntityGUID="7facfe78-d61e-4af9-96a7-ee3e596bb3bb" Json="True" KeyNumber="1613">
            <Value Key="DefaultValue" Value="" Type="String" />
            <Value Key="Disabled" Value="False" Type="Boolean" />
            <Value Key="InputType" Value="string-default" Type="String" />
            <Value Key="Name" Value="Cidade" Type="String" />
            <Value Key="Notes" Value="" Type="String" />
            <Value Key="Required" Value="True" Type="Boolean" />
            <Value Key="ValidationRegExJavaScript" Value="" Type="String" />
            <Value Key="VisibleInEditUI" Value="True" Type="Boolean" />
          </Entity>
          <Entity TargetType="2" AssignmentObjectType="EAV Field Properties" AttributeSetStaticName="@String" AttributeSetName="@String" EntityGUID="b2d88097-c1b8-4406-aab0-694fb9237822" Json="True" KeyNumber="1613" />
          <Entity TargetType="2" AssignmentObjectType="EAV Field Properties" AttributeSetStaticName="@string-default" AttributeSetName="@string-default" EntityGUID="c9d85c49-0b5a-4e73-a3bc-069f46f39fb5" Json="True" KeyNumber="1613" />
        </Attribute>
        <Attribute StaticName="Country" Type="String" IsTitle="false">
          <Entity TargetType="2" AssignmentObjectType="EAV Field Properties" AttributeSetStaticName="@All" AttributeSetName="@All" EntityGUID="0c44ba47-fbba-4412-b173-526e888d653c" Json="True" KeyNumber="1614">
            <Value Key="DefaultValue" Value="" Type="String" />
            <Value Key="Disabled" Value="False" Type="Boolean" />
            <Value Key="InputType" Value="string-default" Type="String" />
            <Value Key="Name" Value="País" Type="String" />
            <Value Key="Notes" Value="" Type="String" />
            <Value Key="Required" Value="False" Type="Boolean" />
            <Value Key="ValidationRegExJavaScript" Value="" Type="String" />
            <Value Key="VisibleInEditUI" Value="True" Type="Boolean" />
          </Entity>
          <Entity TargetType="2" AssignmentObjectType="EAV Field Properties" AttributeSetStaticName="@String" AttributeSetName="@String" EntityGUID="1c9b72ef-82e0-4603-88a5-9a843aa25bb2" Json="True" KeyNumber="1614" />
          <Entity TargetType="2" AssignmentObjectType="EAV Field Properties" AttributeSetStaticName="@string-default" AttributeSetName="@string-default" EntityGUID="b3e9781d-e321-4030-9ea7-3a3da60abc62" Json="True" KeyNumber="1614" />
        </Attribute>
        <Attribute StaticName="CommunicationGroup" Type="Empty" IsTitle="false">
          <Entity TargetType="2" AssignmentObjectType="EAV Field Properties" AttributeSetStaticName="@All" AttributeSetName="@All" EntityGUID="4852bc54-8918-4a62-8440-673cced73c3c" Json="True" KeyNumber="1615">
            <Value Key="CustomJavaScript" Value="" Type="String" />
            <Value Key="DefaultValue" Value="" Type="String" />
            <Value Key="Disabled" Value="False" Type="Boolean" />
            <Value Key="DisableTranslation" Value="False" Type="Boolean" />
            <Value Key="Formulas" Value="null" Type="Entity" />
            <Value Key="InputType" Value="empty-default" Type="String" />
            <Value Key="Name" Value="Informação de contacto" Type="String" />
            <Value Key="Notes" Value="&lt;p&gt;Introduza todas as formas de comunica&amp;ccedil;&amp;atilde;o aqui. Ter em considera&amp;ccedil;&amp;atilde;o que pode adicionar mais campos como twitter, facebook etc. mas isso vai requerer ajuda do seu web designer.&amp;nbsp;&lt;/p&gt;" Type="String" />
            <Value Key="Placeholder" Value="" Type="String" />
            <Value Key="Required" Value="False" Type="Boolean" />
            <Value Key="ValidationRegExJavaScript" Value="" Type="String" />
            <Value Key="VisibleInEditUI" Value="True" Type="Boolean" />
          </Entity>
          <Entity TargetType="2" AssignmentObjectType="EAV Field Properties" AttributeSetStaticName="@empty-default" AttributeSetName="@empty-default" EntityGUID="9ff85ead-b11f-4dc0-ae7e-58fd29193671" Json="True" KeyNumber="1615">
            <Value Key="DefaultCollapsed" Value="True" Type="Boolean" />
          </Entity>
        </Attribute>
        <Attribute StaticName="Tel" Type="String" IsTitle="false">
          <Entity TargetType="2" AssignmentObjectType="EAV Field Properties" AttributeSetStaticName="@All" AttributeSetName="@All" EntityGUID="43c3afeb-b328-46d5-b62f-c8bbd055074e" Json="True" KeyNumber="1616">
            <Value Key="DefaultValue" Value="" Type="String" />
            <Value Key="Disabled" Value="False" Type="Boolean" />
            <Value Key="InputType" Value="string-default" Type="String" />
            <Value Key="Name" Value="Telefone" Type="String" />
            <Value Key="Notes" Value="" Type="String" />
            <Value Key="Required" Value="False" Type="Boolean" />
            <Value Key="ValidationRegExJavaScript" Value="" Type="String" />
            <Value Key="VisibleInEditUI" Value="True" Type="Boolean" />
          </Entity>
          <Entity TargetType="2" AssignmentObjectType="EAV Field Properties" AttributeSetStaticName="@String" AttributeSetName="@String" EntityGUID="503d166e-d776-4569-ac10-6397fc0426db" Json="True" KeyNumber="1616" />
          <Entity TargetType="2" AssignmentObjectType="EAV Field Properties" AttributeSetStaticName="@string-default" AttributeSetName="@string-default" EntityGUID="61c364d1-b625-4b0c-baf4-d523a5dc8e4b" Json="True" KeyNumber="1616" />
        </Attribute>
        <Attribute StaticName="Fax" Type="String" IsTitle="false">
          <Entity TargetType="2" AssignmentObjectType="EAV Field Properties" AttributeSetStaticName="@All" AttributeSetName="@All" EntityGUID="b781bbce-153e-44ea-8231-89b6cb16e197" Json="True" KeyNumber="1617">
            <Value Key="DefaultValue" Value="" Type="String" />
            <Value Key="Disabled" Value="False" Type="Boolean" />
            <Value Key="InputType" Value="string-default" Type="String" />
            <Value Key="Name" Value="Fax" Type="String" />
            <Value Key="Notes" Value="" Type="String" />
            <Value Key="Required" Value="False" Type="Boolean" />
            <Value Key="ValidationRegExJavaScript" Value="" Type="String" />
            <Value Key="VisibleInEditUI" Value="True" Type="Boolean" />
          </Entity>
          <Entity TargetType="2" AssignmentObjectType="EAV Field Properties" AttributeSetStaticName="@String" AttributeSetName="@String" EntityGUID="3b9c3aca-b810-4af5-9f3e-2a4a184ba89c" Json="True" KeyNumber="1617" />
          <Entity TargetType="2" AssignmentObjectType="EAV Field Properties" AttributeSetStaticName="@string-default" AttributeSetName="@string-default" EntityGUID="df98e398-b28b-4dbe-96c1-3d2da2b27fb2" Json="True" KeyNumber="1617" />
        </Attribute>
        <Attribute StaticName="Mail" Type="String" IsTitle="false">
          <Entity TargetType="2" AssignmentObjectType="EAV Field Properties" AttributeSetStaticName="@All" AttributeSetName="@All" EntityGUID="a0128922-eb99-4d75-8f2c-ed675ea4bcf2" Json="True" KeyNumber="1618">
            <Value Key="DefaultValue" Value="" Type="String" />
            <Value Key="Disabled" Value="False" Type="Boolean" />
            <Value Key="InputType" Value="string-default" Type="String" />
            <Value Key="Name" Value="Email" Type="String" />
            <Value Key="Notes" Value="" Type="String" />
            <Value Key="Required" Value="False" Type="Boolean" />
            <Value Key="ValidationRegExJavaScript" Value="" Type="String" />
            <Value Key="VisibleInEditUI" Value="True" Type="Boolean" />
          </Entity>
          <Entity TargetType="2" AssignmentObjectType="EAV Field Properties" AttributeSetStaticName="@String" AttributeSetName="@String" EntityGUID="b91da03d-f7ba-46f0-b35a-927cf9e192e8" Json="True" KeyNumber="1618" />
          <Entity TargetType="2" AssignmentObjectType="EAV Field Properties" AttributeSetStaticName="@string-default" AttributeSetName="@string-default" EntityGUID="cb7571e3-1af4-4b02-a8b5-4e7430ead7ce" Json="True" KeyNumber="1618" />
        </Attribute>
        <Attribute StaticName="GroupGps" Type="Empty" IsTitle="false">
          <Entity TargetType="2" AssignmentObjectType="EAV Field Properties" AttributeSetStaticName="@All" AttributeSetName="@All" EntityGUID="1ea720cc-de28-406c-a5cd-0cef7ce919be" Json="True" KeyNumber="1619">
            <Value Key="CustomJavaScript" Value="" Type="String" />
            <Value Key="DefaultValue" Value="" Type="String" />
            <Value Key="Disabled" Value="False" Type="Boolean" />
            <Value Key="DisableTranslation" Value="False" Type="Boolean" />
            <Value Key="Formulas" Value="null" Type="Entity" />
            <Value Key="InputType" Value="empty-default" Type="String" />
            <Value Key="Name" Value="Coordinadas GPS" Type="String" />
            <Value Key="Notes" Value="&lt;p&gt;Escolha as coordenadas GPS abaixo. Ter em considera&amp;ccedil;&amp;atilde;o que &amp;eacute; muito mais simples se j&amp;aacute; tiver introduzido a morada acima, visto que o pin vai automaticamente centrar nessa localiza&amp;ccedil;&amp;atilde;o.&lt;/p&gt;" Type="String" />
            <Value Key="Placeholder" Value="" Type="String" />
            <Value Key="Required" Value="False" Type="Boolean" />
            <Value Key="ValidationRegExJavaScript" Value="" Type="String" />
            <Value Key="VisibleInEditUI" Value="True" Type="Boolean" />
          </Entity>
          <Entity TargetType="2" AssignmentObjectType="EAV Field Properties" AttributeSetStaticName="@empty-default" AttributeSetName="@empty-default" EntityGUID="1a78a267-5d52-43a0-bdcf-cab55231cef4" Json="True" KeyNumber="1619">
            <Value Key="DefaultCollapsed" Value="True" Type="Boolean" />
          </Entity>
        </Attribute>
        <Attribute StaticName="GPS" Type="Custom" IsTitle="false">
          <Entity TargetType="2" AssignmentObjectType="EAV Field Properties" AttributeSetStaticName="@All" AttributeSetName="@All" EntityGUID="5ec0fd16-8e5a-40e6-8430-816e838f48d9" Json="True" KeyNumber="1620">
            <Value Key="CustomJavaScript" Value="" Type="String" />
            <Value Key="DefaultValue" Value="" Type="String" />
            <Value Key="Disabled" Value="False" Type="Boolean" />
            <Value Key="DisableTranslation" Value="False" Type="Boolean" />
            <Value Key="InputType" Value="custom-gps" Type="String" />
            <Value Key="Name" Value="GPS" Type="String" />
            <Value Key="Notes" Value="" Type="String" />
            <Value Key="Placeholder" Value="" Type="String" />
            <Value Key="Required" Value="False" Type="Boolean" />
            <Value Key="ValidationRegExJavaScript" Value="" Type="String" />
            <Value Key="VisibleInEditUI" Value="True" Type="Boolean" />
          </Entity>
          <Entity TargetType="2" AssignmentObjectType="EAV Field Properties" AttributeSetStaticName="@custom-gps" AttributeSetName="@custom-gps" EntityGUID="7a428d02-9603-4d79-8004-e952ed1fa0e0" Json="True" KeyNumber="1620">
            <Value Key="Address Mask" Value="" Type="String" />
            <Value Key="AddressMask" Value="[Street], [ZipCode]-[City]" Type="String" />
            <Value Key="LatField" Value="" Type="String" />
            <Value Key="LongField" Value="" Type="String" />
          </Entity>
        </Attribute>
        <Attribute StaticName="StreetView" Type="Empty" IsTitle="false">
          <Entity TargetType="2" AssignmentObjectType="EAV Field Properties" AttributeSetStaticName="@All" AttributeSetName="@All" EntityGUID="ba22aed7-4b80-4761-9fc0-beeff11fe863" Json="True" KeyNumber="1648">
            <Value Key="InputType" Value="empty-default" Type="String" />
            <Value Key="Name" Value="StreetView" Type="String" />
            <Value Key="VisibleInEditUI" Value="True" Type="Boolean" />
          </Entity>
        </Attribute>
        <Attribute StaticName="FoV" Type="Number" IsTitle="false">
          <Entity TargetType="2" AssignmentObjectType="EAV Field Properties" AttributeSetStaticName="@All" AttributeSetName="@All" EntityGUID="e5ede018-c534-4941-bd09-c315ce38d4a9" Json="True" KeyNumber="1649">
            <Value Key="CustomJavaScript" Value="" Type="String">
              <Dimension DimensionID="3" ReadOnly="false" />
            </Value>
            <Value Key="DefaultValue" Value="90" Type="String">
              <Dimension DimensionID="3" ReadOnly="false" />
            </Value>
            <Value Key="Disabled" Value="False" Type="Boolean">
              <Dimension DimensionID="3" ReadOnly="false" />
            </Value>
            <Value Key="DisableTranslation" Value="False" Type="Boolean">
              <Dimension DimensionID="3" ReadOnly="false" />
            </Value>
            <Value Key="InputType" Value="number-default" Type="String">
              <Dimension DimensionID="3" ReadOnly="false" />
            </Value>
            <Value Key="IsEphemeral" Value="False" Type="Boolean">
              <Dimension DimensionID="3" ReadOnly="false" />
            </Value>
            <Value Key="Name" Value="FoV" Type="String">
              <Dimension DimensionID="3" ReadOnly="false" />
            </Value>
            <Value Key="Notes" Value="&lt;p&gt;Field of view of the camera&lt;/p&gt;" Type="String">
              <Dimension DimensionID="3" ReadOnly="false" />
            </Value>
            <Value Key="Placeholder" Value="Field of View" Type="String">
              <Dimension DimensionID="3" ReadOnly="false" />
            </Value>
            <Value Key="Required" Value="False" Type="Boolean">
              <Dimension DimensionID="3" ReadOnly="false" />
            </Value>
            <Value Key="ValidationRegExJavaScript" Value="" Type="String">
              <Dimension DimensionID="3" ReadOnly="false" />
            </Value>
            <Value Key="VisibleInEditUI" Value="True" Type="Boolean">
              <Dimension DimensionID="3" ReadOnly="false" />
            </Value>
          </Entity>
          <Entity TargetType="2" AssignmentObjectType="EAV Field Properties" AttributeSetStaticName="@Number" AttributeSetName="@Number" EntityGUID="0c0295fa-6af0-4f0f-a745-b3bfbdf5113c" Json="True" KeyNumber="1649">
            <Value Key="Decimals" Value="0" Type="Number">
              <Dimension DimensionID="3" ReadOnly="false" />
            </Value>
            <Value Key="Max" Value="120" Type="Number">
              <Dimension DimensionID="3" ReadOnly="false" />
            </Value>
            <Value Key="Min" Value="90" Type="Number">
              <Dimension DimensionID="3" ReadOnly="false" />
            </Value>
          </Entity>
        </Attribute>
        <Attribute StaticName="Heading" Type="Number" IsTitle="false">
          <Entity TargetType="2" AssignmentObjectType="EAV Field Properties" AttributeSetStaticName="@All" AttributeSetName="@All" EntityGUID="42a95111-04b9-4331-955f-497e3a332eee" Json="True" KeyNumber="1650">
            <Value Key="CustomJavaScript" Value="" Type="String">
              <Dimension DimensionID="3" ReadOnly="false" />
            </Value>
            <Value Key="DefaultValue" Value="40" Type="String">
              <Dimension DimensionID="3" ReadOnly="false" />
            </Value>
            <Value Key="Disabled" Value="False" Type="Boolean">
              <Dimension DimensionID="3" ReadOnly="false" />
            </Value>
            <Value Key="DisableTranslation" Value="False" Type="Boolean">
              <Dimension DimensionID="3" ReadOnly="false" />
            </Value>
            <Value Key="InputType" Value="number-default" Type="String">
              <Dimension DimensionID="3" ReadOnly="false" />
            </Value>
            <Value Key="IsEphemeral" Value="False" Type="Boolean">
              <Dimension DimensionID="3" ReadOnly="false" />
            </Value>
            <Value Key="Name" Value="Heading" Type="String">
              <Dimension DimensionID="3" ReadOnly="false" />
            </Value>
            <Value Key="Notes" Value="&lt;p&gt;You have 360 degree to choose&lt;/p&gt;" Type="String">
              <Dimension DimensionID="3" ReadOnly="false" />
            </Value>
            <Value Key="Placeholder" Value="Where the camera is headed to" Type="String">
              <Dimension DimensionID="3" ReadOnly="false" />
            </Value>
            <Value Key="Required" Value="False" Type="Boolean">
              <Dimension DimensionID="3" ReadOnly="false" />
            </Value>
            <Value Key="ValidationRegExJavaScript" Value="" Type="String">
              <Dimension DimensionID="3" ReadOnly="false" />
            </Value>
            <Value Key="VisibleInEditUI" Value="True" Type="Boolean">
              <Dimension DimensionID="3" ReadOnly="false" />
            </Value>
          </Entity>
          <Entity TargetType="2" AssignmentObjectType="EAV Field Properties" AttributeSetStaticName="@Number" AttributeSetName="@Number" EntityGUID="dde012b0-6506-4491-837d-b4f1049941d9" Json="True" KeyNumber="1650">
            <Value Key="Decimals" Value="0" Type="Number">
              <Dimension DimensionID="3" ReadOnly="false" />
            </Value>
            <Value Key="Max" Value="360" Type="Number">
              <Dimension DimensionID="3" ReadOnly="false" />
            </Value>
            <Value Key="Min" Value="0" Type="Number">
              <Dimension DimensionID="3" ReadOnly="false" />
            </Value>
          </Entity>
        </Attribute>
        <Attribute StaticName="Pitch" Type="Number" IsTitle="false">
          <Entity TargetType="2" AssignmentObjectType="EAV Field Properties" AttributeSetStaticName="@All" AttributeSetName="@All" EntityGUID="731bc2b3-99b6-4b13-8b3e-eea15393db1d" Json="True" KeyNumber="1651">
            <Value Key="CustomJavaScript" Value="" Type="String">
              <Dimension DimensionID="3" ReadOnly="false" />
            </Value>
            <Value Key="DefaultValue" Value="0" Type="String">
              <Dimension DimensionID="3" ReadOnly="false" />
            </Value>
            <Value Key="Disabled" Value="False" Type="Boolean">
              <Dimension DimensionID="3" ReadOnly="false" />
            </Value>
            <Value Key="DisableTranslation" Value="False" Type="Boolean">
              <Dimension DimensionID="3" ReadOnly="false" />
            </Value>
            <Value Key="InputType" Value="number-default" Type="String">
              <Dimension DimensionID="3" ReadOnly="false" />
            </Value>
            <Value Key="IsEphemeral" Value="False" Type="Boolean">
              <Dimension DimensionID="3" ReadOnly="false" />
            </Value>
            <Value Key="Name" Value="Pitch" Type="String">
              <Dimension DimensionID="3" ReadOnly="false" />
            </Value>
            <Value Key="Notes" Value="&lt;p&gt;Enter the Pitch value&lt;/p&gt;" Type="String">
              <Dimension DimensionID="3" ReadOnly="false" />
            </Value>
            <Value Key="Placeholder" Value="Pitch" Type="String">
              <Dimension DimensionID="3" ReadOnly="false" />
            </Value>
            <Value Key="Required" Value="False" Type="Boolean">
              <Dimension DimensionID="3" ReadOnly="false" />
            </Value>
            <Value Key="ValidationRegExJavaScript" Value="" Type="String">
              <Dimension DimensionID="3" ReadOnly="false" />
            </Value>
            <Value Key="VisibleInEditUI" Value="True" Type="Boolean">
              <Dimension DimensionID="3" ReadOnly="false" />
            </Value>
          </Entity>
          <Entity TargetType="2" AssignmentObjectType="EAV Field Properties" AttributeSetStaticName="@Number" AttributeSetName="@Number" EntityGUID="58449974-10b9-46f5-a990-1d9554710a1d" Json="True" KeyNumber="1651">
            <Value Key="Decimals" Value="0" Type="Number">
              <Dimension DimensionID="3" ReadOnly="false" />
            </Value>
            <Value Key="Max" Value="90" Type="Number">
              <Dimension DimensionID="3" ReadOnly="false" />
            </Value>
            <Value Key="Min" Value="-90" Type="Number">
              <Dimension DimensionID="3" ReadOnly="false" />
            </Value>
          </Entity>
        </Attribute>
      </Attributes>
    </AttributeSet>
    <AttributeSet StaticName="3168c0b7-9999-4aa8-9ada-773890339e58" Name="LocationMap" Description="Location / Address" Scope="Default" AlwaysShareConfiguration="false">
      <Attributes>
        <Attribute StaticName="MapName" Type="String" IsTitle="true">
          <Entity TargetType="2" AssignmentObjectType="EAV Field Properties" AttributeSetStaticName="@All" AttributeSetName="@All" EntityGUID="49482d46-58ad-4fa2-82f5-96c798170ae7" Json="True" KeyNumber="1638">
            <Value Key="CustomJavaScript" Value="" Type="String">
              <Dimension DimensionID="3" ReadOnly="false" />
            </Value>
            <Value Key="DefaultValue" Value="" Type="String">
              <Dimension DimensionID="3" ReadOnly="false" />
            </Value>
            <Value Key="Disabled" Value="False" Type="Boolean">
              <Dimension DimensionID="3" ReadOnly="false" />
            </Value>
            <Value Key="DisableTranslation" Value="False" Type="Boolean">
              <Dimension DimensionID="3" ReadOnly="false" />
            </Value>
            <Value Key="InputType" Value="string-default" Type="String">
              <Dimension DimensionID="3" ReadOnly="false" />
            </Value>
            <Value Key="Name" Value="Nome do Mapa" Type="String">
              <Dimension DimensionID="3" ReadOnly="false" />
            </Value>
            <Value Key="Notes" Value="" Type="String">
              <Dimension DimensionID="3" ReadOnly="false" />
            </Value>
            <Value Key="Placeholder" Value="" Type="String">
              <Dimension DimensionID="3" ReadOnly="false" />
            </Value>
            <Value Key="Required" Value="False" Type="Boolean">
              <Dimension DimensionID="3" ReadOnly="false" />
            </Value>
            <Value Key="ValidationRegExJavaScript" Value="" Type="String">
              <Dimension DimensionID="3" ReadOnly="false" />
            </Value>
            <Value Key="VisibleInEditUI" Value="True" Type="Boolean">
              <Dimension DimensionID="3" ReadOnly="false" />
            </Value>
          </Entity>
          <Entity TargetType="2" AssignmentObjectType="EAV Field Properties" AttributeSetStaticName="@String" AttributeSetName="@String" EntityGUID="0e572fd3-c8d7-406f-959f-8fe5b747b7f0" Json="True" KeyNumber="1638">
            <Value Key="DropdownValues" Value="" Type="String">
              <Dimension DimensionID="3" ReadOnly="false" />
            </Value>
            <Value Key="InputType" Value="" Type="String">
              <Dimension DimensionID="3" ReadOnly="false" />
            </Value>
          </Entity>
          <Entity TargetType="2" AssignmentObjectType="EAV Field Properties" AttributeSetStaticName="@string-default" AttributeSetName="@string-default" EntityGUID="e1efee02-268d-4b73-8998-889e2f447e7e" Json="True" KeyNumber="1638">
            <Value Key="InputFontFamily" Value="" Type="String">
              <Dimension DimensionID="3" ReadOnly="false" />
            </Value>
          </Entity>
        </Attribute>
        <Attribute StaticName="Description" Type="String" IsTitle="false">
          <Entity TargetType="2" AssignmentObjectType="EAV Field Properties" AttributeSetStaticName="@All" AttributeSetName="@All" EntityGUID="0046030d-25d7-4584-aa43-bb08f0df7a84" Json="True" KeyNumber="1625">
            <Value Key="CustomJavaScript" Value="" Type="String">
              <Dimension DimensionID="3" ReadOnly="false" />
            </Value>
            <Value Key="DefaultValue" Value="" Type="String">
              <Dimension DimensionID="3" ReadOnly="false" />
            </Value>
            <Value Key="Disabled" Value="False" Type="Boolean">
              <Dimension DimensionID="3" ReadOnly="false" />
            </Value>
            <Value Key="DisableTranslation" Value="False" Type="Boolean">
              <Dimension DimensionID="3" ReadOnly="false" />
            </Value>
            <Value Key="InputType" Value="string-default" Type="String">
              <Dimension DimensionID="3" ReadOnly="false" />
            </Value>
            <Value Key="Name" Value="Descrição curta" Type="String">
              <Dimension DimensionID="3" ReadOnly="false" />
            </Value>
            <Value Key="Notes" Value="&lt;p&gt;Descri&amp;ccedil;&amp;atilde;o do endere&amp;ccedil;o - ser&amp;aacute; mostrado em alguns templates.&lt;/p&gt;" Type="String">
              <Dimension DimensionID="3" ReadOnly="false" />
            </Value>
            <Value Key="Placeholder" Value="" Type="String">
              <Dimension DimensionID="3" ReadOnly="false" />
            </Value>
            <Value Key="Required" Value="False" Type="Boolean">
              <Dimension DimensionID="3" ReadOnly="false" />
            </Value>
            <Value Key="ValidationRegExJavaScript" Value="" Type="String">
              <Dimension DimensionID="3" ReadOnly="false" />
            </Value>
            <Value Key="VisibleInEditUI" Value="True" Type="Boolean">
              <Dimension DimensionID="3" ReadOnly="false" />
            </Value>
          </Entity>
          <Entity TargetType="2" AssignmentObjectType="EAV Field Properties" AttributeSetStaticName="@String" AttributeSetName="@String" EntityGUID="78d64ac4-6050-41ec-b98c-8a8f8249983d" Json="True" KeyNumber="1625">
            <Value Key="DropdownValues" Value="" Type="String">
              <Dimension DimensionID="3" ReadOnly="false" />
            </Value>
            <Value Key="InputType" Value="wysiwyg" Type="String">
              <Dimension DimensionID="3" ReadOnly="false" />
            </Value>
            <Value Key="RowCount" Value="1" Type="Number">
              <Dimension DimensionID="3" ReadOnly="false" />
            </Value>
          </Entity>
          <Entity TargetType="2" AssignmentObjectType="EAV Field Properties" AttributeSetStaticName="@string-wysiwyg" AttributeSetName="@string-wysiwyg" EntityGUID="6e8f971d-486f-4897-8354-20d8118c3411" Json="True" KeyNumber="1625">
            <Value Key="ButtonAdvanced" Value="" Type="String" />
            <Value Key="ButtonSource" Value="" Type="String" />
            <Value Key="ContentCss" Value="" Type="Hyperlink" />
            <Value Key="Dialog" Value="" Type="String" />
            <Value Key="InlineInitialHeight" Value="" Type="String" />
          </Entity>
          <Entity TargetType="2" AssignmentObjectType="EAV Field Properties" AttributeSetStaticName="@string-default" AttributeSetName="@string-default" EntityGUID="a067f53c-ad6d-4463-ae74-eb2b1bfd5d80" Json="True" KeyNumber="1625">
            <Value Key="InputFontFamily" Value="" Type="String">
              <Dimension DimensionID="3" ReadOnly="false" />
            </Value>
            <Value Key="RowCount" Value="2" Type="Number">
              <Dimension DimensionID="3" ReadOnly="false" />
            </Value>
          </Entity>
        </Attribute>
        <Attribute StaticName="Icon" Type="Hyperlink" IsTitle="false">
          <Entity TargetType="2" AssignmentObjectType="EAV Field Properties" AttributeSetStaticName="@All" AttributeSetName="@All" EntityGUID="555f66e8-3d10-4244-8ee1-9b6605e9e3c8" Json="True" KeyNumber="1642">
            <Value Key="CustomJavaScript" Value="" Type="String">
              <Dimension DimensionID="3" ReadOnly="false" />
            </Value>
            <Value Key="DefaultValue" Value="https://icon-library.com/images/google-maps-bus-icon/google-maps-bus-icon-3.jpg" Type="String">
              <Dimension DimensionID="3" ReadOnly="false" />
            </Value>
            <Value Key="Disabled" Value="False" Type="Boolean">
              <Dimension DimensionID="3" ReadOnly="false" />
            </Value>
            <Value Key="DisableTranslation" Value="False" Type="Boolean">
              <Dimension DimensionID="3" ReadOnly="false" />
            </Value>
            <Value Key="InputType" Value="hyperlink-default" Type="String">
              <Dimension DimensionID="3" ReadOnly="false" />
            </Value>
            <Value Key="Name" Value="Icon" Type="String">
              <Dimension DimensionID="3" ReadOnly="false" />
            </Value>
            <Value Key="Notes" Value="" Type="String">
              <Dimension DimensionID="3" ReadOnly="false" />
            </Value>
            <Value Key="Placeholder" Value="" Type="String">
              <Dimension DimensionID="3" ReadOnly="false" />
            </Value>
            <Value Key="Required" Value="False" Type="Boolean">
              <Dimension DimensionID="3" ReadOnly="false" />
            </Value>
            <Value Key="ValidationRegExJavaScript" Value="" Type="String">
              <Dimension DimensionID="3" ReadOnly="false" />
            </Value>
            <Value Key="VisibleInEditUI" Value="True" Type="Boolean">
              <Dimension DimensionID="3" ReadOnly="false" />
            </Value>
          </Entity>
          <Entity TargetType="2" AssignmentObjectType="EAV Field Properties" AttributeSetStaticName="@Hyperlink" AttributeSetName="@Hyperlink" EntityGUID="64449721-a7eb-43bf-ab32-37a63630277f" Json="True" KeyNumber="1642">
            <Value Key="Buttons" Value="adam,more" Type="String">
              <Dimension DimensionID="3" ReadOnly="false" />
            </Value>
            <Value Key="DefaultDialog" Value="" Type="String">
              <Dimension DimensionID="3" ReadOnly="false" />
            </Value>
            <Value Key="FileFilter" Value="" Type="String">
              <Dimension DimensionID="3" ReadOnly="false" />
            </Value>
            <Value Key="Paths" Value="" Type="String">
              <Dimension DimensionID="3" ReadOnly="false" />
            </Value>
            <Value Key="ServerResourceMapping" Value="" Type="String">
              <Dimension DimensionID="3" ReadOnly="false" />
            </Value>
            <Value Key="ShowAdam" Value="True" Type="Boolean">
              <Dimension DimensionID="3" ReadOnly="false" />
            </Value>
            <Value Key="ShowFileManager" Value="False" Type="Boolean">
              <Dimension DimensionID="3" ReadOnly="false" />
            </Value>
            <Value Key="ShowImageManager" Value="False" Type="Boolean">
              <Dimension DimensionID="3" ReadOnly="false" />
            </Value>
            <Value Key="ShowPagePicker" Value="False" Type="Boolean">
              <Dimension DimensionID="3" ReadOnly="false" />
            </Value>
          </Entity>
        </Attribute>
        <Attribute StaticName="AddressGroup" Type="Empty" IsTitle="false">
          <Entity TargetType="2" AssignmentObjectType="EAV Field Properties" AttributeSetStaticName="@All" AttributeSetName="@All" EntityGUID="c05004a7-7bc4-4724-a062-4da34d45a3de" Json="True" KeyNumber="1626">
            <Value Key="CustomJavaScript" Value="" Type="String">
              <Dimension DimensionID="3" ReadOnly="false" />
            </Value>
            <Value Key="DefaultValue" Value="" Type="String">
              <Dimension DimensionID="3" ReadOnly="false" />
            </Value>
            <Value Key="Disabled" Value="False" Type="Boolean">
              <Dimension DimensionID="3" ReadOnly="false" />
            </Value>
            <Value Key="DisableTranslation" Value="False" Type="Boolean">
              <Dimension DimensionID="3" ReadOnly="false" />
            </Value>
            <Value Key="InputType" Value="empty-default" Type="String">
              <Dimension DimensionID="3" ReadOnly="false" />
            </Value>
            <Value Key="Name" Value="Endereço do Centro do Mapa" Type="String">
              <Dimension DimensionID="3" ReadOnly="false" />
            </Value>
            <Value Key="Notes" Value="" Type="String">
              <Dimension DimensionID="3" ReadOnly="false" />
            </Value>
            <Value Key="Placeholder" Value="" Type="String">
              <Dimension DimensionID="3" ReadOnly="false" />
            </Value>
            <Value Key="Required" Value="False" Type="Boolean">
              <Dimension DimensionID="3" ReadOnly="false" />
            </Value>
            <Value Key="ValidationRegExJavaScript" Value="" Type="String">
              <Dimension DimensionID="3" ReadOnly="false" />
            </Value>
            <Value Key="VisibleInEditUI" Value="True" Type="Boolean">
              <Dimension DimensionID="3" ReadOnly="false" />
            </Value>
          </Entity>
          <Entity TargetType="2" AssignmentObjectType="EAV Field Properties" AttributeSetStaticName="@empty-default" AttributeSetName="@empty-default" EntityGUID="a969cfe0-08c1-43ae-a128-dc704a733429" Json="True" KeyNumber="1626">
            <Value Key="DefaultCollapsed" Value="False" Type="Boolean">
              <Dimension DimensionID="3" ReadOnly="false" />
            </Value>
          </Entity>
        </Attribute>
        <Attribute StaticName="Street" Type="String" IsTitle="false">
          <Entity TargetType="2" AssignmentObjectType="EAV Field Properties" AttributeSetStaticName="@All" AttributeSetName="@All" EntityGUID="4ff8c22b-2b90-4616-957a-aaae56eb5e7a" Json="True" KeyNumber="1627">
            <Value Key="DefaultValue" Value="" Type="String" />
            <Value Key="Disabled" Value="False" Type="Boolean" />
            <Value Key="InputType" Value="string-default" Type="String" />
            <Value Key="Name" Value="Rua" Type="String" />
            <Value Key="Notes" Value="" Type="String" />
            <Value Key="Required" Value="False" Type="Boolean" />
            <Value Key="ValidationRegExJavaScript" Value="" Type="String" />
            <Value Key="VisibleInEditUI" Value="True" Type="Boolean" />
          </Entity>
          <Entity TargetType="2" AssignmentObjectType="EAV Field Properties" AttributeSetStaticName="@String" AttributeSetName="@String" EntityGUID="9dd6de75-a572-43e9-bd19-beedc8cfa384" Json="True" KeyNumber="1627" />
          <Entity TargetType="2" AssignmentObjectType="EAV Field Properties" AttributeSetStaticName="@string-default" AttributeSetName="@string-default" EntityGUID="965d6148-8376-4fec-af51-c5c94beda097" Json="True" KeyNumber="1627">
            <Value Key="RowCount" Value="3" Type="Number" />
          </Entity>
        </Attribute>
        <Attribute StaticName="ZipCode" Type="String" IsTitle="false">
          <Entity TargetType="2" AssignmentObjectType="EAV Field Properties" AttributeSetStaticName="@All" AttributeSetName="@All" EntityGUID="4c5645ec-c1d7-4075-b47b-22288af85777" Json="True" KeyNumber="1628">
            <Value Key="DefaultValue" Value="" Type="String" />
            <Value Key="Disabled" Value="False" Type="Boolean" />
            <Value Key="InputType" Value="string-default" Type="String" />
            <Value Key="Name" Value="Código Postal" Type="String" />
            <Value Key="Notes" Value="" Type="String" />
            <Value Key="Required" Value="False" Type="Boolean" />
            <Value Key="ValidationRegExJavaScript" Value="" Type="String" />
            <Value Key="VisibleInEditUI" Value="True" Type="Boolean" />
          </Entity>
          <Entity TargetType="2" AssignmentObjectType="EAV Field Properties" AttributeSetStaticName="@String" AttributeSetName="@String" EntityGUID="654bcf6a-e2dc-42f4-b346-fca7705b7780" Json="True" KeyNumber="1628" />
          <Entity TargetType="2" AssignmentObjectType="EAV Field Properties" AttributeSetStaticName="@string-default" AttributeSetName="@string-default" EntityGUID="cb573b32-1fdd-49b5-914e-aa09532ef1f3" Json="True" KeyNumber="1628" />
        </Attribute>
        <Attribute StaticName="City" Type="String" IsTitle="false">
          <Entity TargetType="2" AssignmentObjectType="EAV Field Properties" AttributeSetStaticName="@All" AttributeSetName="@All" EntityGUID="7facfe78-d61e-4af9-96a7-ee3e596bb3bb" Json="True" KeyNumber="1629">
            <Value Key="DefaultValue" Value="" Type="String" />
            <Value Key="Disabled" Value="False" Type="Boolean" />
            <Value Key="InputType" Value="string-default" Type="String" />
            <Value Key="Name" Value="Cidade" Type="String" />
            <Value Key="Notes" Value="" Type="String" />
            <Value Key="Required" Value="True" Type="Boolean" />
            <Value Key="ValidationRegExJavaScript" Value="" Type="String" />
            <Value Key="VisibleInEditUI" Value="True" Type="Boolean" />
          </Entity>
          <Entity TargetType="2" AssignmentObjectType="EAV Field Properties" AttributeSetStaticName="@String" AttributeSetName="@String" EntityGUID="b2d88097-c1b8-4406-aab0-694fb9237822" Json="True" KeyNumber="1629" />
          <Entity TargetType="2" AssignmentObjectType="EAV Field Properties" AttributeSetStaticName="@string-default" AttributeSetName="@string-default" EntityGUID="c9d85c49-0b5a-4e73-a3bc-069f46f39fb5" Json="True" KeyNumber="1629" />
        </Attribute>
        <Attribute StaticName="Country" Type="String" IsTitle="false">
          <Entity TargetType="2" AssignmentObjectType="EAV Field Properties" AttributeSetStaticName="@All" AttributeSetName="@All" EntityGUID="0c44ba47-fbba-4412-b173-526e888d653c" Json="True" KeyNumber="1630">
            <Value Key="DefaultValue" Value="" Type="String" />
            <Value Key="Disabled" Value="False" Type="Boolean" />
            <Value Key="InputType" Value="string-default" Type="String" />
            <Value Key="Name" Value="País" Type="String" />
            <Value Key="Notes" Value="" Type="String" />
            <Value Key="Required" Value="False" Type="Boolean" />
            <Value Key="ValidationRegExJavaScript" Value="" Type="String" />
            <Value Key="VisibleInEditUI" Value="True" Type="Boolean" />
          </Entity>
          <Entity TargetType="2" AssignmentObjectType="EAV Field Properties" AttributeSetStaticName="@String" AttributeSetName="@String" EntityGUID="1c9b72ef-82e0-4603-88a5-9a843aa25bb2" Json="True" KeyNumber="1630" />
          <Entity TargetType="2" AssignmentObjectType="EAV Field Properties" AttributeSetStaticName="@string-default" AttributeSetName="@string-default" EntityGUID="b3e9781d-e321-4030-9ea7-3a3da60abc62" Json="True" KeyNumber="1630" />
        </Attribute>
        <Attribute StaticName="GroupGps" Type="Empty" IsTitle="false">
          <Entity TargetType="2" AssignmentObjectType="EAV Field Properties" AttributeSetStaticName="@All" AttributeSetName="@All" EntityGUID="1ea720cc-de28-406c-a5cd-0cef7ce919be" Json="True" KeyNumber="1635">
            <Value Key="CustomJavaScript" Value="" Type="String">
              <Dimension DimensionID="3" ReadOnly="false" />
            </Value>
            <Value Key="DefaultValue" Value="" Type="String">
              <Dimension DimensionID="3" ReadOnly="false" />
            </Value>
            <Value Key="Disabled" Value="False" Type="Boolean">
              <Dimension DimensionID="3" ReadOnly="false" />
            </Value>
            <Value Key="DisableTranslation" Value="False" Type="Boolean">
              <Dimension DimensionID="3" ReadOnly="false" />
            </Value>
            <Value Key="Formulas" Value="null" Type="Entity" />
            <Value Key="InputType" Value="empty-default" Type="String">
              <Dimension DimensionID="3" ReadOnly="false" />
            </Value>
            <Value Key="Name" Value="Coordenadas GPS" Type="String">
              <Dimension DimensionID="3" ReadOnly="false" />
            </Value>
            <Value Key="Notes" Value="&lt;p&gt;Escolha as coordenadas GPS abaixo. Ter em considera&amp;ccedil;&amp;atilde;o que &amp;eacute; muito mais simples se j&amp;aacute; tiver introduzido a morada acima, visto que o pin vai automaticamente centrar nessa localiza&amp;ccedil;&amp;atilde;o.&lt;/p&gt;" Type="String">
              <Dimension DimensionID="3" ReadOnly="false" />
            </Value>
            <Value Key="Placeholder" Value="" Type="String">
              <Dimension DimensionID="3" ReadOnly="false" />
            </Value>
            <Value Key="Required" Value="False" Type="Boolean">
              <Dimension DimensionID="3" ReadOnly="false" />
            </Value>
            <Value Key="ValidationRegExJavaScript" Value="" Type="String">
              <Dimension DimensionID="3" ReadOnly="false" />
            </Value>
            <Value Key="VisibleInEditUI" Value="True" Type="Boolean">
              <Dimension DimensionID="3" ReadOnly="false" />
            </Value>
          </Entity>
          <Entity TargetType="2" AssignmentObjectType="EAV Field Properties" AttributeSetStaticName="@empty-default" AttributeSetName="@empty-default" EntityGUID="1a78a267-5d52-43a0-bdcf-cab55231cef4" Json="True" KeyNumber="1635">
            <Value Key="DefaultCollapsed" Value="True" Type="Boolean">
              <Dimension DimensionID="3" ReadOnly="false" />
            </Value>
          </Entity>
        </Attribute>
        <Attribute StaticName="GPS" Type="Custom" IsTitle="false">
          <Entity TargetType="2" AssignmentObjectType="EAV Field Properties" AttributeSetStaticName="@All" AttributeSetName="@All" EntityGUID="5ec0fd16-8e5a-40e6-8430-816e838f48d9" Json="True" KeyNumber="1636">
            <Value Key="CustomJavaScript" Value="" Type="String" />
            <Value Key="DefaultValue" Value="" Type="String" />
            <Value Key="Disabled" Value="False" Type="Boolean" />
            <Value Key="DisableTranslation" Value="False" Type="Boolean" />
            <Value Key="InputType" Value="custom-gps" Type="String" />
            <Value Key="Name" Value="GPS" Type="String" />
            <Value Key="Notes" Value="" Type="String" />
            <Value Key="Placeholder" Value="" Type="String" />
            <Value Key="Required" Value="False" Type="Boolean" />
            <Value Key="ValidationRegExJavaScript" Value="" Type="String" />
            <Value Key="VisibleInEditUI" Value="True" Type="Boolean" />
          </Entity>
          <Entity TargetType="2" AssignmentObjectType="EAV Field Properties" AttributeSetStaticName="@custom-gps" AttributeSetName="@custom-gps" EntityGUID="7a428d02-9603-4d79-8004-e952ed1fa0e0" Json="True" KeyNumber="1636">
            <Value Key="Address Mask" Value="" Type="String" />
            <Value Key="AddressMask" Value="[Street], [ZipCode]-[City]" Type="String" />
            <Value Key="LatField" Value="" Type="String" />
            <Value Key="LongField" Value="" Type="String" />
          </Entity>
        </Attribute>
        <Attribute StaticName="GoogleMapsConfiguration" Type="Empty" IsTitle="false">
          <Entity TargetType="2" AssignmentObjectType="EAV Field Properties" AttributeSetStaticName="@All" AttributeSetName="@All" EntityGUID="32752dfe-6a8b-430d-bda1-6a22e578e029" Json="True" KeyNumber="1644">
            <Value Key="CustomJavaScript" Value="" Type="String">
              <Dimension DimensionID="3" ReadOnly="false" />
            </Value>
            <Value Key="DefaultValue" Value="" Type="String">
              <Dimension DimensionID="3" ReadOnly="false" />
            </Value>
            <Value Key="Disabled" Value="False" Type="Boolean">
              <Dimension DimensionID="3" ReadOnly="false" />
            </Value>
            <Value Key="DisableTranslation" Value="False" Type="Boolean">
              <Dimension DimensionID="3" ReadOnly="false" />
            </Value>
            <Value Key="InputType" Value="empty-default" Type="String">
              <Dimension DimensionID="3" ReadOnly="false" />
            </Value>
            <Value Key="Name" Value="Configurações do Google Maps" Type="String">
              <Dimension DimensionID="3" ReadOnly="false" />
            </Value>
            <Value Key="Notes" Value="" Type="String">
              <Dimension DimensionID="3" ReadOnly="false" />
            </Value>
            <Value Key="Placeholder" Value="" Type="String">
              <Dimension DimensionID="3" ReadOnly="false" />
            </Value>
            <Value Key="Required" Value="False" Type="Boolean">
              <Dimension DimensionID="3" ReadOnly="false" />
            </Value>
            <Value Key="ValidationRegExJavaScript" Value="" Type="String">
              <Dimension DimensionID="3" ReadOnly="false" />
            </Value>
            <Value Key="VisibleInEditUI" Value="True" Type="Boolean">
              <Dimension DimensionID="3" ReadOnly="false" />
            </Value>
          </Entity>
          <Entity TargetType="2" AssignmentObjectType="EAV Field Properties" AttributeSetStaticName="@empty-default" AttributeSetName="@empty-default" EntityGUID="dd3b26f5-12cc-4397-8a48-5b22d9ae6024" Json="True" KeyNumber="1644">
            <Value Key="DefaultCollapsed" Value="False" Type="Boolean">
              <Dimension DimensionID="3" ReadOnly="false" />
            </Value>
          </Entity>
        </Attribute>
        <Attribute StaticName="ZoomLevel" Type="Number" IsTitle="false">
          <Entity TargetType="2" AssignmentObjectType="EAV Field Properties" AttributeSetStaticName="@All" AttributeSetName="@All" EntityGUID="2a8b20ad-ff44-4b95-bdf2-f1a1a0602724" Json="True" KeyNumber="1639">
            <Value Key="InputType" Value="number-default" Type="String" />
            <Value Key="Name" Value="ZoomLevel" Type="String" />
            <Value Key="VisibleInEditUI" Value="True" Type="Boolean" />
          </Entity>
        </Attribute>
        <Attribute StaticName="Tilt" Type="Number" IsTitle="false">
          <Entity TargetType="2" AssignmentObjectType="EAV Field Properties" AttributeSetStaticName="@All" AttributeSetName="@All" EntityGUID="88a32780-0a8d-4958-8e82-f627370f91a9" Json="True" KeyNumber="1640">
            <Value Key="InputType" Value="number-default" Type="String" />
            <Value Key="Name" Value="Tilt" Type="String" />
            <Value Key="VisibleInEditUI" Value="True" Type="Boolean" />
          </Entity>
        </Attribute>
        <Attribute StaticName="GestureHandling" Type="String" IsTitle="false">
          <Entity TargetType="2" AssignmentObjectType="EAV Field Properties" AttributeSetStaticName="@All" AttributeSetName="@All" EntityGUID="f5345280-525f-4fc8-adb0-e5cdd003ed43" Json="True" KeyNumber="1643">
            <Value Key="CustomJavaScript" Value="" Type="String">
              <Dimension DimensionID="3" ReadOnly="false" />
            </Value>
            <Value Key="DefaultValue" Value="" Type="String">
              <Dimension DimensionID="3" ReadOnly="false" />
            </Value>
            <Value Key="Disabled" Value="False" Type="Boolean">
              <Dimension DimensionID="3" ReadOnly="false" />
            </Value>
            <Value Key="DisableTranslation" Value="False" Type="Boolean">
              <Dimension DimensionID="3" ReadOnly="false" />
            </Value>
            <Value Key="InputType" Value="string-dropdown" Type="String">
              <Dimension DimensionID="3" ReadOnly="false" />
            </Value>
            <Value Key="Name" Value="Gesture Handling" Type="String">
              <Dimension DimensionID="3" ReadOnly="false" />
            </Value>
            <Value Key="Notes" Value="" Type="String">
              <Dimension DimensionID="3" ReadOnly="false" />
            </Value>
            <Value Key="Placeholder" Value="" Type="String">
              <Dimension DimensionID="3" ReadOnly="false" />
            </Value>
            <Value Key="Required" Value="False" Type="Boolean">
              <Dimension DimensionID="3" ReadOnly="false" />
            </Value>
            <Value Key="ValidationRegExJavaScript" Value="" Type="String">
              <Dimension DimensionID="3" ReadOnly="false" />
            </Value>
            <Value Key="VisibleInEditUI" Value="True" Type="Boolean">
              <Dimension DimensionID="3" ReadOnly="false" />
            </Value>
          </Entity>
          <Entity TargetType="2" AssignmentObjectType="EAV Field Properties" AttributeSetStaticName="@String" AttributeSetName="@String" EntityGUID="d00d5b31-eedb-4ebb-8b2a-129f2cc39b1a" Json="True" KeyNumber="1643">
            <Value Key="DropdownValues" Value="" Type="String">
              <Dimension DimensionID="3" ReadOnly="false" />
            </Value>
            <Value Key="InputType" Value="" Type="String">
              <Dimension DimensionID="3" ReadOnly="false" />
            </Value>
          </Entity>
          <Entity TargetType="2" AssignmentObjectType="EAV Field Properties" AttributeSetStaticName="@string-dropdown" AttributeSetName="@string-dropdown" EntityGUID="75065bcf-0e66-4a6d-be98-42eafd9a2ff2" Json="True" KeyNumber="1643">
            <Value Key="DropdownValues" Value="none:Nenhum&#xA;cooperative:Cooperativo&#xA;greedy:Fominha&#xA;auto:Automatico" Type="String">
              <Dimension DimensionID="3" ReadOnly="false" />
            </Value>
            <Value Key="DropdownValuesFormat" Value="value-label" Type="String">
              <Dimension DimensionID="3" ReadOnly="false" />
            </Value>
            <Value Key="EnableTextEntry" Value="False" Type="Boolean">
              <Dimension DimensionID="3" ReadOnly="false" />
            </Value>
          </Entity>
        </Attribute>
        <Attribute StaticName="MapType" Type="String" IsTitle="false">
          <Entity TargetType="2" AssignmentObjectType="EAV Field Properties" AttributeSetStaticName="@All" AttributeSetName="@All" EntityGUID="e258ccd8-9851-4c96-b9b5-b57a3c8f10dc" Json="True" KeyNumber="1645">
            <Value Key="CustomJavaScript" Value="" Type="String">
              <Dimension DimensionID="3" ReadOnly="false" />
            </Value>
            <Value Key="DefaultValue" Value="roadmap" Type="String">
              <Dimension DimensionID="3" ReadOnly="false" />
            </Value>
            <Value Key="Disabled" Value="False" Type="Boolean">
              <Dimension DimensionID="3" ReadOnly="false" />
            </Value>
            <Value Key="DisableTranslation" Value="False" Type="Boolean">
              <Dimension DimensionID="3" ReadOnly="false" />
            </Value>
            <Value Key="InputType" Value="string-dropdown" Type="String">
              <Dimension DimensionID="3" ReadOnly="false" />
            </Value>
            <Value Key="Name" Value="MapType" Type="String">
              <Dimension DimensionID="3" ReadOnly="false" />
            </Value>
            <Value Key="Notes" Value="&lt;p&gt;HYBRID This map type displays a transparent layer of major streets on satellite images.&lt;br /&gt;ROADMAP This map type displays a normal street map.&lt;br /&gt;SATELLITE This map type displays satellite images.&lt;br /&gt;TERRAIN This map type displays maps with physical features such as terrain and vegetation.&lt;/p&gt;" Type="String">
              <Dimension DimensionID="3" ReadOnly="false" />
            </Value>
            <Value Key="Placeholder" Value="Tipo de Mapa" Type="String">
              <Dimension DimensionID="3" ReadOnly="false" />
            </Value>
            <Value Key="Required" Value="False" Type="Boolean">
              <Dimension DimensionID="3" ReadOnly="false" />
            </Value>
            <Value Key="ValidationRegExJavaScript" Value="" Type="String">
              <Dimension DimensionID="3" ReadOnly="false" />
            </Value>
            <Value Key="VisibleInEditUI" Value="True" Type="Boolean">
              <Dimension DimensionID="3" ReadOnly="false" />
            </Value>
          </Entity>
          <Entity TargetType="2" AssignmentObjectType="EAV Field Properties" AttributeSetStaticName="@String" AttributeSetName="@String" EntityGUID="2b671b78-e9e6-4413-91dc-ebdd91ed3ef3" Json="True" KeyNumber="1645">
            <Value Key="DropdownValues" Value="" Type="String">
              <Dimension DimensionID="3" ReadOnly="false" />
            </Value>
            <Value Key="InputType" Value="" Type="String">
              <Dimension DimensionID="3" ReadOnly="false" />
            </Value>
          </Entity>
          <Entity TargetType="2" AssignmentObjectType="EAV Field Properties" AttributeSetStaticName="@string-dropdown" AttributeSetName="@string-dropdown" EntityGUID="03028ed6-d71c-40a6-b86c-275cdae219d4" Json="True" KeyNumber="1645">
            <Value Key="DropdownValues" Value="hybrid:Hibrido&#xA;roadmap:Ruas&#xA;satellite:Satelite&#xA;terrain:Terreno" Type="String">
              <Dimension DimensionID="3" ReadOnly="false" />
            </Value>
            <Value Key="DropdownValuesFormat" Value="value-label" Type="String">
              <Dimension DimensionID="3" ReadOnly="false" />
            </Value>
            <Value Key="EnableTextEntry" Value="False" Type="Boolean">
              <Dimension DimensionID="3" ReadOnly="false" />
            </Value>
          </Entity>
        </Attribute>
        <Attribute StaticName="MarkerMode" Type="String" IsTitle="false">
          <Entity TargetType="2" AssignmentObjectType="EAV Field Properties" AttributeSetStaticName="@All" AttributeSetName="@All" EntityGUID="741c505a-ff2a-4c1a-9a42-ff491562018e" Json="True" KeyNumber="1646">
            <Value Key="CustomJavaScript" Value="" Type="String">
              <Dimension DimensionID="3" ReadOnly="false" />
            </Value>
            <Value Key="DefaultValue" Value="" Type="String">
              <Dimension DimensionID="3" ReadOnly="false" />
            </Value>
            <Value Key="Disabled" Value="False" Type="Boolean">
              <Dimension DimensionID="3" ReadOnly="false" />
            </Value>
            <Value Key="DisableTranslation" Value="False" Type="Boolean">
              <Dimension DimensionID="3" ReadOnly="false" />
            </Value>
            <Value Key="InputType" Value="string-dropdown" Type="String">
              <Dimension DimensionID="3" ReadOnly="false" />
            </Value>
            <Value Key="Name" Value="MarkerMode" Type="String">
              <Dimension DimensionID="3" ReadOnly="false" />
            </Value>
            <Value Key="Notes" Value="" Type="String">
              <Dimension DimensionID="3" ReadOnly="false" />
            </Value>
            <Value Key="Placeholder" Value="" Type="String">
              <Dimension DimensionID="3" ReadOnly="false" />
            </Value>
            <Value Key="Required" Value="False" Type="Boolean">
              <Dimension DimensionID="3" ReadOnly="false" />
            </Value>
            <Value Key="ValidationRegExJavaScript" Value="" Type="String">
              <Dimension DimensionID="3" ReadOnly="false" />
            </Value>
            <Value Key="VisibleInEditUI" Value="True" Type="Boolean">
              <Dimension DimensionID="3" ReadOnly="false" />
            </Value>
          </Entity>
          <Entity TargetType="2" AssignmentObjectType="EAV Field Properties" AttributeSetStaticName="@String" AttributeSetName="@String" EntityGUID="ce22f57d-a609-48c8-8d45-e8234d061204" Json="True" KeyNumber="1646">
            <Value Key="DropdownValues" Value="" Type="String">
              <Dimension DimensionID="3" ReadOnly="false" />
            </Value>
            <Value Key="InputType" Value="" Type="String">
              <Dimension DimensionID="3" ReadOnly="false" />
            </Value>
          </Entity>
          <Entity TargetType="2" AssignmentObjectType="EAV Field Properties" AttributeSetStaticName="@string-dropdown" AttributeSetName="@string-dropdown" EntityGUID="c42b67d7-c693-485a-911b-7106ec11af08" Json="True" KeyNumber="1646">
            <Value Key="DropdownValues" Value="ToggleVisibility:Show or Hide on Click&#xA;CenterFocus:Close others and Center on Click" Type="String">
              <Dimension DimensionID="3" ReadOnly="false" />
            </Value>
            <Value Key="DropdownValuesFormat" Value="value-label" Type="String">
              <Dimension DimensionID="3" ReadOnly="false" />
            </Value>
            <Value Key="EnableTextEntry" Value="False" Type="Boolean">
              <Dimension DimensionID="3" ReadOnly="false" />
            </Value>
          </Entity>
        </Attribute>
        <Attribute StaticName="ApiKey" Type="String" IsTitle="false">
          <Entity TargetType="2" AssignmentObjectType="EAV Field Properties" AttributeSetStaticName="@All" AttributeSetName="@All" EntityGUID="1ab68f04-a440-4b1a-9106-154ea1a25e66" Json="True" KeyNumber="1647">
            <Value Key="InputType" Value="string-default" Type="String" />
            <Value Key="Name" Value="ApiKey" Type="String" />
            <Value Key="VisibleInEditUI" Value="True" Type="Boolean" />
          </Entity>
        </Attribute>
      </Attributes>
    </AttributeSet>
    <AttributeSet StaticName="ef3be8fc-1c17-4680-8306-73a44fde53c6" Name="PresSetMap" Description="Settings for the map template (Standort Karte)" Scope="Default" AlwaysShareConfiguration="false">
      <Attributes>
        <Attribute StaticName="MapsLabelDirections" Type="String" IsTitle="true">
          <Entity TargetType="2" AssignmentObjectType="EAV Field Properties" AttributeSetStaticName="@All" AttributeSetName="@All" EntityGUID="eecc95b1-2474-4c68-8130-209386e7180c" Json="True" KeyNumber="1621">
            <Value Key="CustomJavaScript" Value="" Type="String" />
            <Value Key="DefaultValue" Value="Directions" Type="String" />
            <Value Key="Disabled" Value="False" Type="Boolean" />
            <Value Key="DisableTranslation" Value="False" Type="Boolean" />
            <Value Key="InputType" Value="string-default" Type="String" />
            <Value Key="Name" Value="Link for Driving Directions" Type="String" />
            <Value Key="Notes" Value="&lt;p&gt;This label is used for the link bringing the user to google maps in from-to mode. Leave empty to default from App Resources.&amp;nbsp;&lt;/p&gt;" Type="String" />
            <Value Key="Placeholder" Value="" Type="String" />
            <Value Key="Required" Value="False" Type="Boolean" />
            <Value Key="ValidationRegExJavaScript" Value="" Type="String" />
            <Value Key="VisibleInEditUI" Value="True" Type="Boolean" />
          </Entity>
          <Entity TargetType="2" AssignmentObjectType="EAV Field Properties" AttributeSetStaticName="@String" AttributeSetName="@String" EntityGUID="1a490169-accc-4057-9efb-17ca7d4e3ee4" Json="True" KeyNumber="1621">
            <Value Key="DropdownValues" Value="" Type="String" />
            <Value Key="InputType" Value="" Type="String" />
          </Entity>
          <Entity TargetType="2" AssignmentObjectType="EAV Field Properties" AttributeSetStaticName="@string-default" AttributeSetName="@string-default" EntityGUID="0d337c41-0ec9-4b3c-bb08-5b54184cb17c" Json="True" KeyNumber="1621">
            <Value Key="InputFontFamily" Value="" Type="String" />
          </Entity>
        </Attribute>
        <Attribute StaticName="MapsEnableDirections" Type="Boolean" IsTitle="false">
          <Entity TargetType="2" AssignmentObjectType="EAV Field Properties" AttributeSetStaticName="@All" AttributeSetName="@All" EntityGUID="a390257c-ca1f-478e-b84f-a5056cd4e18e" Json="True" KeyNumber="1622">
            <Value Key="CustomJavaScript" Value="" Type="String" />
            <Value Key="DefaultValue" Value="" Type="String" />
            <Value Key="Disabled" Value="False" Type="Boolean" />
            <Value Key="DisableTranslation" Value="False" Type="Boolean" />
            <Value Key="InputType" Value="boolean-tristate" Type="String" />
            <Value Key="Name" Value="Enable Directions Button on Maps" Type="String" />
            <Value Key="Notes" Value="" Type="String" />
            <Value Key="Placeholder" Value="" Type="String" />
            <Value Key="Required" Value="False" Type="Boolean" />
            <Value Key="ValidationRegExJavaScript" Value="" Type="String" />
            <Value Key="VisibleInEditUI" Value="True" Type="Boolean" />
          </Entity>
          <Entity TargetType="2" AssignmentObjectType="EAV Field Properties" AttributeSetStaticName="@Boolean" AttributeSetName="@Boolean" EntityGUID="420a58f2-3736-4a21-99e8-be9adb80a33d" Json="True" KeyNumber="1622">
            <Value Key="TitleFalse" Value="" Type="String" />
            <Value Key="TitleIndeterminate" Value="" Type="String" />
            <Value Key="TitleTrue" Value="" Type="String" />
          </Entity>
        </Attribute>
      </Attributes>
    </AttributeSet>
  </AttributeSets>
  <Entities>
    <Entity TargetType="3" AssignmentObjectType="App" AttributeSetStaticName="2SexyContent-App" AttributeSetName="2SexyContent-App" EntityGUID="1b6a7076-5e7e-4876-8449-fcc33d338f0c" Json="True" KeyNumber="116">
      <Value Key="AllowRazorTemplates" Value="True" Type="Boolean">
        <Dimension DimensionID="3" ReadOnly="false" />
      </Value>
      <Value Key="AllowTokenTemplates" Value="True" Type="Boolean">
        <Dimension DimensionID="3" ReadOnly="false" />
      </Value>
      <Value Key="Description" Value="Turn your Google Maps in a Sexy Maps app" Type="String">
        <Dimension DimensionID="3" ReadOnly="false" />
      </Value>
      <Value Key="DisplayName" Value="Google Sexy Maps" Type="String">
        <Dimension DimensionID="3" ReadOnly="false" />
      </Value>
      <Value Key="Folder" Value="Google Sexy Maps" Type="String">
        <Dimension DimensionID="3" ReadOnly="false" />
      </Value>
      <Value Key="Hidden" Value="False" Type="Boolean">
        <Dimension DimensionID="3" ReadOnly="false" />
      </Value>
      <Value Key="OriginalId" Value="" Type="String">
        <Dimension DimensionID="3" ReadOnly="false" />
      </Value>
      <Value Key="RequiredDnnVersion" Value="07.02.00" Type="String">
        <Dimension DimensionID="3" ReadOnly="false" />
      </Value>
      <Value Key="RequiredOqtaneVersion" Value="" Type="String">
        <Dimension DimensionID="3" ReadOnly="false" />
      </Value>
      <Value Key="RequiredVersion" Value="08.03.00" Type="String">
        <Dimension DimensionID="3" ReadOnly="false" />
      </Value>
      <Value Key="SupportsAjaxReload" Value="False" Type="Boolean">
        <Dimension DimensionID="3" ReadOnly="false" />
      </Value>
      <Value Key="Version" Value="00.00.15" Type="String">
        <Dimension DimensionID="3" ReadOnly="false" />
      </Value>
    </Entity>
    <Entity TargetType="3" AssignmentObjectType="App" AttributeSetStaticName="App-Settings" AttributeSetName="App-Settings" EntityGUID="62921a25-bfc0-4c0e-9e54-1f356a998600" KeyNumber="116" />
    <Entity TargetType="3" AssignmentObjectType="App" AttributeSetStaticName="App-Resources" AttributeSetName="App-Resources" EntityGUID="f1026b9e-45d7-487f-a9e9-820d4ee0c7b4" KeyNumber="116" />
    <Entity TargetType="1" AssignmentObjectType="Default" AttributeSetStaticName="2SexyContent-Template" AttributeSetName="2SexyContent-Template" EntityGUID="19551585-f9d4-44e2-89ae-be312fb978af" Json="True">
      <Value Key="ContentDemoEntity" Value="54e877f8-f291-49a1-8813-61941e9543c7" Type="Entity" />
      <Value Key="ContentTypeStaticName" Value="3168c0b7-c5b9-4aa8-9ada-773890339e58" Type="String">
        <Dimension DimensionID="3" ReadOnly="false" />
      </Value>
      <Value Key="Icon" Value="" Type="Hyperlink">
        <Dimension DimensionID="3" ReadOnly="false" />
      </Value>
      <Value Key="Identifier" Value="" Type="String">
        <Dimension DimensionID="3" ReadOnly="false" />
      </Value>
      <Value Key="IsHidden" Value="False" Type="Boolean">
        <Dimension DimensionID="3" ReadOnly="false" />
      </Value>
      <Value Key="ListContentDemoEntity" Value="4da6e2bd-3bf4-40b7-b1fa-b1bb83df0cc1" Type="Entity" />
      <Value Key="ListContentTypeStaticName" Value="3168c0b7-9999-4aa8-9ada-773890339e58" Type="String">
        <Dimension DimensionID="3" ReadOnly="false" />
      </Value>
      <Value Key="ListPresentationTypeStaticName" Value="" Type="String">
        <Dimension DimensionID="3" ReadOnly="false" />
      </Value>
      <Value Key="Location" Value="Site" Type="String">
        <Dimension DimensionID="3" ReadOnly="false" />
      </Value>
      <Value Key="Name" Value="GMapView Multiple Pins" Type="String">
        <Dimension DimensionID="3" ReadOnly="false" />
      </Value>
      <Value Key="Path" Value="_MapView 01.cshtml" Type="String">
        <Dimension DimensionID="3" ReadOnly="false" />
      </Value>
      <Value Key="PresentationDemoEntity" Value="6f9e4db4-3f50-4fc0-817f-263c6ec28cc3" Type="Entity" />
      <Value Key="PresentationTypeStaticName" Value="ef3be8fc-1c17-4680-8306-73a44fde53c6" Type="String">
        <Dimension DimensionID="3" ReadOnly="false" />
      </Value>
      <Value Key="PublishData" Value="False" Type="Boolean">
        <Dimension DimensionID="3" ReadOnly="false" />
      </Value>
      <Value Key="SearchIndexingDisabled" Value="False" Type="Boolean">
        <Dimension DimensionID="3" ReadOnly="false" />
      </Value>
      <Value Key="SearchIndexingStreams" Value="" Type="String">
        <Dimension DimensionID="3" ReadOnly="false" />
      </Value>
      <Value Key="StreamsToPublish" Value="" Type="String">
        <Dimension DimensionID="3" ReadOnly="false" />
      </Value>
      <Value Key="Type" Value="C# Razor" Type="String">
        <Dimension DimensionID="3" ReadOnly="false" />
      </Value>
      <Value Key="UseForList" Value="True" Type="Boolean">
        <Dimension DimensionID="3" ReadOnly="false" />
      </Value>
      <Value Key="ViewController" Value="" Type="String">
        <Dimension DimensionID="3" ReadOnly="false" />
      </Value>
      <Value Key="ViewNameInUrl" Value="" Type="String">
        <Dimension DimensionID="3" ReadOnly="false" />
      </Value>
    </Entity>
    <Entity TargetType="5" AssignmentObjectType="ContentType" AttributeSetStaticName="ContentType" AttributeSetName="ContentType" EntityGUID="cb492860-4f4b-4841-90bb-15107d97baf5" Json="True" KeyString="3168c0b7-c5b9-4aa8-9ada-773890339e58">
      <Value Key="Description" Value="Para mapa com endereço" Type="String" />
      <Value Key="DynamicChildrenField" Value="" Type="String" />
      <Value Key="EditInstructions" Value="" Type="String" />
      <Value Key="Icon" Value="[App:Path]/Icons/Type-Icon-Location.png" Type="Hyperlink" />
      <Value Key="Label" Value="Localização / endereço" Type="String" />
      <Value Key="Link" Value="https://github.com/2sic/2sxc-content-bootstrap3/wiki/Help" Type="Hyperlink" />
      <Value Key="ListInstructions" Value="" Type="String" />
      <Value Key="Notes" Value="" Type="String" />
    </Entity>
    <Entity TargetType="5" AssignmentObjectType="ContentType" AttributeSetStaticName="ContentType" AttributeSetName="ContentType" EntityGUID="07de9445-dcf6-4b21-b2db-56fdfffd98f3" Json="True" KeyString="ef3be8fc-1c17-4680-8306-73a44fde53c6">
      <Value Key="Description" Value="Definições para Template de Google Maps (Standort Karte)" Type="String" />
      <Value Key="DynamicChildrenField" Value="" Type="String" />
      <Value Key="EditInstructions" Value="" Type="String" />
      <Value Key="Icon" Value="" Type="Hyperlink" />
      <Value Key="Label" Value="Definições de apresentação para Templates de Mapas" Type="String" />
      <Value Key="Link" Value="https://github.com/2sic/2sxc-content-bootstrap3/wiki/Help" Type="Hyperlink" />
      <Value Key="ListInstructions" Value="" Type="String" />
      <Value Key="Notes" Value="" Type="String" />
    </Entity>
    <Entity TargetType="1" AssignmentObjectType="Default" AttributeSetStaticName="ef3be8fc-1c17-4680-8306-73a44fde53c6" AttributeSetName="PresSetMap" EntityGUID="6f9e4db4-3f50-4fc0-817f-263c6ec28cc3">
      <Value Key="MapsEnableDirections" Value="True" Type="Boolean">
        <Dimension DimensionID="3" ReadOnly="false" />
      </Value>
      <Value Key="MapsLabelDirections" Value="Directions" Type="String">
        <Dimension DimensionID="3" ReadOnly="false" />
      </Value>
    </Entity>
    <Entity TargetType="1" AssignmentObjectType="Default" AttributeSetStaticName="3168c0b7-c5b9-4aa8-9ada-773890339e58" AttributeSetName="Location" EntityGUID="54e877f8-f291-49a1-8813-61941e9543c7">
      <Value Key="City" Value="Salvador" Type="String">
        <Dimension DimensionID="3" ReadOnly="false" />
      </Value>
      <Value Key="Country" Value="Brasil" Type="String">
        <Dimension DimensionID="3" ReadOnly="false" />
      </Value>
      <Value Key="Description" Value="&lt;p&gt;Centro de Educa&amp;ccedil;&amp;atilde;o Profissional Aquidab&amp;atilde;&lt;/p&gt;" Type="String">
        <Dimension DimensionID="3" ReadOnly="false" />
      </Value>
      <Value Key="Fax" Value="" Type="String">
        <Dimension DimensionID="3" ReadOnly="false" />
      </Value>
      <Value Key="FoV" Value="115" Type="Number">
        <Dimension DimensionID="3" ReadOnly="false" />
      </Value>
      <Value Key="GPS" Value="{&quot;latitude&quot;:-12.968871,&quot;longitude&quot;:-38.5046018}" Type="Custom">
        <Dimension DimensionID="3" ReadOnly="false" />
      </Value>
      <Value Key="Heading" Value="200" Type="Number">
        <Dimension DimensionID="3" ReadOnly="false" />
      </Value>
      <Value Key="Icon" Value="https://icon-library.com/images/google-maps-bus-icon/google-maps-bus-icon-3.jpg" Type="Hyperlink">
        <Dimension DimensionID="3" ReadOnly="false" />
      </Value>
      <Value Key="Mail" Value="aquidaba@ba.domain.br" Type="String">
        <Dimension DimensionID="3" ReadOnly="false" />
      </Value>
      <Value Key="Pitch" Value="12" Type="Number">
        <Dimension DimensionID="3" ReadOnly="false" />
      </Value>
      <Value Key="Street" Value="Av. José Joaquim Seabra, 403" Type="String">
        <Dimension DimensionID="3" ReadOnly="false" />
      </Value>
      <Value Key="Tel" Value="(71) 3186-4000" Type="String">
        <Dimension DimensionID="3" ReadOnly="false" />
      </Value>
      <Value Key="Title" Value="Unidade Móvel Aquidabã" Type="String">
        <Dimension DimensionID="3" ReadOnly="false" />
      </Value>
      <Value Key="ZipCode" Value="40025-000" Type="String">
        <Dimension DimensionID="3" ReadOnly="false" />
      </Value>
    </Entity>
    <Entity TargetType="5" AssignmentObjectType="ContentType" AttributeSetStaticName="ContentType" AttributeSetName="ContentType" EntityGUID="cb492860-4f4b-4841-90bb-15107d97baf5" Json="True" KeyString="3168c0b7-9999-4aa8-9ada-773890339e58">
      <Value Key="Description" Value="Para mapa com endereço" Type="String">
        <Dimension DimensionID="3" ReadOnly="false" />
      </Value>
      <Value Key="DynamicChildrenField" Value="" Type="String">
        <Dimension DimensionID="3" ReadOnly="false" />
      </Value>
      <Value Key="EditInstructions" Value="" Type="String">
        <Dimension DimensionID="3" ReadOnly="false" />
      </Value>
      <Value Key="Icon" Value="[App:Path]/Icons/Type-Icon-Location.png" Type="Hyperlink">
        <Dimension DimensionID="3" ReadOnly="false" />
      </Value>
      <Value Key="Label" Value="Região do Mapa" Type="String">
        <Dimension DimensionID="3" ReadOnly="false" />
      </Value>
      <Value Key="Link" Value="https://github.com/2sic/2sxc-content-bootstrap3/wiki/Help" Type="Hyperlink">
        <Dimension DimensionID="3" ReadOnly="false" />
      </Value>
      <Value Key="ListInstructions" Value="" Type="String">
        <Dimension DimensionID="3" ReadOnly="false" />
      </Value>
      <Value Key="Notes" Value="" Type="String">
        <Dimension DimensionID="3" ReadOnly="false" />
      </Value>
    </Entity>
    <Entity TargetType="1" AssignmentObjectType="Default" AttributeSetStaticName="3168c0b7-9999-4aa8-9ada-773890339e58" AttributeSetName="LocationMap" EntityGUID="4da6e2bd-3bf4-40b7-b1fa-b1bb83df0cc1">
      <Value Key="ApiKey" Value="AIzaSyBgSAoSiD7xVP9dNZLhNy6PgIwKTYSSA9k" Type="String">
        <Dimension DimensionID="3" ReadOnly="false" />
      </Value>
      <Value Key="City" Value="Salvador" Type="String">
        <Dimension DimensionID="3" ReadOnly="false" />
      </Value>
      <Value Key="Country" Value="Brasil" Type="String">
        <Dimension DimensionID="3" ReadOnly="false" />
      </Value>
      <Value Key="Description" Value="Veja onde estão nossas unidades itinerantes e vá conhecer!" Type="String">
        <Dimension DimensionID="3" ReadOnly="false" />
      </Value>
      <Value Key="GestureHandling" Value="auto" Type="String">
        <Dimension DimensionID="3" ReadOnly="false" />
      </Value>
      <Value Key="GPS" Value="{&quot;latitude&quot;:-12.968494613725385,&quot;longitude&quot;:-38.475312077557376}" Type="Custom">
        <Dimension DimensionID="3" ReadOnly="false" />
      </Value>
      <Value Key="Icon" Value="https://icon-library.com/images/google-maps-bus-icon/google-maps-bus-icon-3.jpg" Type="Hyperlink">
        <Dimension DimensionID="3" ReadOnly="false" />
      </Value>
      <Value Key="MapName" Value="Unidades Móveis" Type="String">
        <Dimension DimensionID="3" ReadOnly="false" />
      </Value>
      <Value Key="MapType" Value="roadmap" Type="String">
        <Dimension DimensionID="3" ReadOnly="false" />
      </Value>
      <Value Key="MarkerMode" Value="CenterFocus" Type="String">
        <Dimension DimensionID="3" ReadOnly="false" />
      </Value>
      <Value Key="Street" Value="Av. José Joaquim Seabra, 403 - Baixa dos Sapateiros&#xA;" Type="String">
        <Dimension DimensionID="3" ReadOnly="false" />
      </Value>
      <Value Key="Tilt" Value="45" Type="Number">
        <Dimension DimensionID="3" ReadOnly="false" />
      </Value>
      <Value Key="ZipCode" Value="40025-000" Type="String">
        <Dimension DimensionID="3" ReadOnly="false" />
      </Value>
      <Value Key="ZoomLevel" Value="14" Type="Number">
        <Dimension DimensionID="3" ReadOnly="false" />
      </Value>
    </Entity>
    <Entity TargetType="1" AssignmentObjectType="Default" AttributeSetStaticName="f5764f60-2621-4a5d-9391-100fbe664640" AttributeSetName="⚙️GoogleMaps" EntityGUID="bc582709-9683-4f62-9d60-af278aee6565" Json="True">
      <Value Key="ApiKey" Value="AIzaSyBgSAoSiD7xVP9dNZLhNy6PgIwKTYSSA9k" Type="String">
        <Dimension DimensionID="3" ReadOnly="false" />
      </Value>
      <Value Key="MarkerIcon" Value="" Type="Hyperlink">
        <Dimension DimensionID="3" ReadOnly="false" />
      </Value>
      <Value Key="SettingsIdentifier" Value="GoogleMaps" Type="String">
        <Dimension DimensionID="3" ReadOnly="false" />
      </Value>
      <Value Key="Zoom" Value="12" Type="Number">
        <Dimension DimensionID="3" ReadOnly="false" />
      </Value>
    </Entity>
    <Entity TargetType="1" AssignmentObjectType="Default" AttributeSetStaticName="3168c0b7-c5b9-4aa8-9ada-773890339e58" AttributeSetName="Location" EntityGUID="a9a35913-6e7b-4c3c-98d1-0b1dca8f48a4">
      <Value Key="City" Value="Salvador" Type="String">
        <Dimension DimensionID="3" ReadOnly="false" />
      </Value>
      <Value Key="Country" Value="Brasil" Type="String">
        <Dimension DimensionID="3" ReadOnly="false" />
      </Value>
      <Value Key="Description" Value="&lt;p&gt;Centro de Educa&amp;ccedil;&amp;atilde;o Profissional Casa do Com&amp;eacute;rcio&lt;/p&gt;" Type="String">
        <Dimension DimensionID="3" ReadOnly="false" />
      </Value>
      <Value Key="Fax" Value="" Type="String">
        <Dimension DimensionID="3" ReadOnly="false" />
      </Value>
      <Value Key="FoV" Value="110" Type="Number">
        <Dimension DimensionID="3" ReadOnly="false" />
      </Value>
      <Value Key="GPS" Value="{&quot;latitude&quot;:-12.980301,&quot;longitude&quot;:-38.4564529}" Type="Custom">
        <Dimension DimensionID="3" ReadOnly="false" />
      </Value>
      <Value Key="Heading" Value="40" Type="Number">
        <Dimension DimensionID="3" ReadOnly="false" />
      </Value>
      <Value Key="Icon" Value="https://icon-library.com/images/google-maps-bus-icon/google-maps-bus-icon-3.jpg" Type="Hyperlink">
        <Dimension DimensionID="3" ReadOnly="false" />
      </Value>
      <Value Key="Mail" Value="" Type="String">
        <Dimension DimensionID="3" ReadOnly="false" />
      </Value>
      <Value Key="Pitch" Value="27" Type="Number">
        <Dimension DimensionID="3" ReadOnly="false" />
      </Value>
      <Value Key="Street" Value="Av. Tancredo Neves, 1109 - Pituba" Type="String">
        <Dimension DimensionID="3" ReadOnly="false" />
      </Value>
      <Value Key="Tel" Value="" Type="String">
        <Dimension DimensionID="3" ReadOnly="false" />
      </Value>
      <Value Key="Title" Value="Unidade Móvel da Casa do Comércio" Type="String">
        <Dimension DimensionID="3" ReadOnly="false" />
      </Value>
      <Value Key="ZipCode" Value="41820-021" Type="String">
        <Dimension DimensionID="3" ReadOnly="false" />
      </Value>
    </Entity>
    <Entity TargetType="1" AssignmentObjectType="Default" AttributeSetStaticName="3168c0b7-c5b9-4aa8-9ada-773890339e58" AttributeSetName="Location" EntityGUID="22546b6f-b564-4fb6-ae92-d6947cb71288">
      <Value Key="City" Value="Salvador " Type="String">
        <Dimension DimensionID="3" ReadOnly="false" />
      </Value>
      <Value Key="Country" Value="Brasil" Type="String">
        <Dimension DimensionID="3" ReadOnly="false" />
      </Value>
      <Value Key="Description" Value="&lt;p&gt;Centro de Educa&amp;ccedil;&amp;atilde;o Hoteleira Pelourinho&lt;/p&gt;" Type="String">
        <Dimension DimensionID="3" ReadOnly="false" />
      </Value>
      <Value Key="Fax" Value="" Type="String">
        <Dimension DimensionID="3" ReadOnly="false" />
      </Value>
      <Value Key="FoV" Value="115" Type="Number">
        <Dimension DimensionID="3" ReadOnly="false" />
      </Value>
      <Value Key="GPS" Value="{&quot;latitude&quot;:-12.9714143,&quot;longitude&quot;:-38.5083661}" Type="Custom">
        <Dimension DimensionID="3" ReadOnly="false" />
      </Value>
      <Value Key="Heading" Value="112" Type="Number">
        <Dimension DimensionID="3" ReadOnly="false" />
      </Value>
      <Value Key="Icon" Value="https://icon-library.com/images/google-maps-bus-icon/google-maps-bus-icon-3.jpg" Type="Hyperlink">
        <Dimension DimensionID="3" ReadOnly="false" />
      </Value>
      <Value Key="Mail" Value="" Type="String">
        <Dimension DimensionID="3" ReadOnly="false" />
      </Value>
      <Value Key="Pitch" Value="28" Type="Number">
        <Dimension DimensionID="3" ReadOnly="false" />
      </Value>
      <Value Key="Street" Value="Largo do Pelourinho - Pelourinho" Type="String">
        <Dimension DimensionID="3" ReadOnly="false" />
      </Value>
      <Value Key="Tel" Value="" Type="String">
        <Dimension DimensionID="3" ReadOnly="false" />
      </Value>
      <Value Key="Title" Value="Unidade Móvel Pelourinho" Type="String">
        <Dimension DimensionID="3" ReadOnly="false" />
      </Value>
      <Value Key="ZipCode" Value="40026280" Type="String">
        <Dimension DimensionID="3" ReadOnly="false" />
      </Value>
    </Entity>
  </Entities>
  <PortalFiles />
  <PortalFolders>
    <Folder Id="1725" RelativePath="adam/Google Sexy Maps/" />
  </PortalFolders>
</SexyContent>